contaminante/.python-version
contaminante/__init__.py
contaminante/contaminante.py
contaminante/gaia.py
contaminante/version.py
contaminante-0.5.7.dist-info/LICENSE
contaminante-0.5.7.dist-info/WHEEL
contaminante-0.5.7.dist-info/METADATA
contaminante-0.5.7.dist-info/RECORD
