Metadata-Version: 2.1
Name: contaminante
Version: 0.5.7
Summary: A package to help find the contaminant transiting source in NASA's *Kepler*, *K2* or *TESS* data.
License: MIT
Author: Christina Hedges
Author-email: christina.l.hedges@nasa.gov
Requires-Python: >=3.8,<3.10
Classifier: License :: OSI Approved :: MIT License
Classifier: Programming Language :: Python :: 3
Classifier: Programming Language :: Python :: 3.8
Classifier: Programming Language :: Python :: 3.9
Requires-Dist: astropy (>=4.3.1,<5.0.0)
Requires-Dist: lightkurve (>=2.0.11,<3.0.0)
Requires-Dist: matplotlib (>=3.4.3,<4.0.0)
Requires-Dist: numpy (>=1.21.3,<2.0.0)
Requires-Dist: pandas (>=1.3.4,<2.0.0)
Requires-Dist: scipy (>=1.7.1,<2.0.0)
Requires-Dist: tqdm (>=4.62.3,<5.0.0)
